python-emailer/__init__.py
python-emailer/email_processing.py
python-emailer/tests/__init__.py
python-emailer/tests/test_email_processing.py
python_emailer/__init__.py
python_emailer/email_processing.py
python_emailer/tes1.py
python_emailer/tests/__init__.py
python_emailer/tests/test_email_processing.py
python_emailer-1.5.0.dist-info/LICENSE
python_emailer-1.5.0.dist-info/METADATA
python_emailer-1.5.0.dist-info/WHEEL
python_emailer-1.5.0.dist-info/top_level.txt
python_emailer-1.5.0.dist-info/RECORD
